isss/__init__.py
isss/script/__init__.py
isss/stubs/__init__.py
isss-1.0.2.data/scripts/isss-fw
isss-1.0.2.data/scripts/isss-license-formatter
isss-1.0.2.dist-info/LICENSE
isss-1.0.2.dist-info/METADATA
isss-1.0.2.dist-info/WHEEL
isss-1.0.2.dist-info/top_level.txt
isss-1.0.2.dist-info/RECORD
