Metadata-Version: 2.1
Name: isss
Version: 1.0.2
Summary: A unofficial library which provides wrappers around IBM Security Secret Server REST APIs. Also compatible with Thycotic Secret Server
Home-page: https://www.ibm.com/marketplace/secret-server
Author: Romain Lienard
Author-email: rlienard@fr.ibm.com
License: UNKNOWN
Keywords: isss,ibm,thycotic,secret,server
Platform: UNKNOWN
Classifier: Programming Language :: Python :: 3
Classifier: License :: OSI Approved :: Apache Software License
Classifier: Operating System :: OS Independent
